uniarray/__init__.py
uniarray-0.0.1.dist-info/METADATA
uniarray-0.0.1.dist-info/WHEEL
uniarray-0.0.1.dist-info/RECORD
