Metadata-Version: 2.4
Name: uniarray
Version: 0.0.1
Summary: Device-agnostic array library (coming soon)
Author: Dror
License: MIT
Requires-Python: >=3.9
